qc_robyn_admin/__init__.py
qc_robyn_admin/auth_admin.py
qc_robyn_admin/auth_models.py
qc_robyn_admin/models.py
qc_robyn_admin/core/__init__.py
qc_robyn_admin/core/admin.py
qc_robyn_admin/core/fields.py
qc_robyn_admin/core/filters.py
qc_robyn_admin/core/inline.py
qc_robyn_admin/core/menu.py
qc_robyn_admin/core/site.py
qc_robyn_admin/core/__pycache__/__init__.cpython-311.pyc
qc_robyn_admin/core/__pycache__/admin.cpython-311.pyc
qc_robyn_admin/core/__pycache__/fields.cpython-311.pyc
qc_robyn_admin/core/__pycache__/filters.cpython-311.pyc
qc_robyn_admin/core/__pycache__/inline.cpython-311.pyc
qc_robyn_admin/core/__pycache__/menu.cpython-311.pyc
qc_robyn_admin/core/__pycache__/site.cpython-311.pyc
qc_robyn_admin/i18n/translations.py
qc_robyn_admin/i18n/__pycache__/translations.cpython-311.pyc
qc_robyn_admin/orm/base.py
qc_robyn_admin/orm/tortoise.py
qc_robyn_admin/renderers/base.py
qc_robyn_admin/templates/admin/base.html
qc_robyn_admin/templates/admin/index.html
qc_robyn_admin/templates/admin/login.html
qc_robyn_admin/templates/admin/model_form.html
qc_robyn_admin/templates/admin/model_list.html
qc_robyn_admin/templates/admin/components/data_table.html
qc_robyn_admin/templates/admin/components/filter_panel.html
qc_robyn_admin/templates/admin/components/form_modal.html
qc_robyn_admin/templates/admin/components/header.html
qc_robyn_admin/templates/admin/components/inline_modal.html
qc_robyn_admin/templates/admin/components/sidebar.html
qc_robyn_admin-0.1.5.dist-info/LICENSE
qc_robyn_admin-0.1.5.dist-info/METADATA
qc_robyn_admin-0.1.5.dist-info/WHEEL
qc_robyn_admin-0.1.5.dist-info/top_level.txt
qc_robyn_admin-0.1.5.dist-info/RECORD
