Metadata-Version: 2.1
Name: qc-robyn-admin
Version: 0.1.5
Summary: A backend framework based on Robyn and Tortoise-ORM
Home-page: https://github.com/0x7eQiChen/robyn-admin
Author: 0x7eQiChen
Author-email: 0x7eQiChen <1356617750@qq.com>
License: MIT
Requires-Python: >=3.8
License-File: LICENSE
Requires-Dist: robyn>=0.1.0
Requires-Dist: tortoise-orm>=0.19.0
Requires-Dist: jinja2>=3.0.0
Requires-Dist: pandas>=1.0.0
Requires-Dist: openpyxl>=3.0.0
Requires-Dist: aiosqlite>=0.17.0
